pysproto/__init__.py
pysproto/_sproto.c
pysproto/_sproto.pypy310-pp73-win_amd64.pyd
pysproto/_sproto.pyx
pysproto/sproto.pxd
pysproto/sprotodump.py
pysproto/sprotoparser.py
sproto-0.1.4.dist-info/LICENSE
sproto-0.1.4.dist-info/METADATA
sproto-0.1.4.dist-info/WHEEL
sproto-0.1.4.dist-info/top_level.txt
sproto-0.1.4.dist-info/RECORD
